obsidian_git_uploader/__init__.py
obsidian_git_uploader/convert.py
obsidian_git_uploader/image_upload.py
obsidian_git_uploader-1.0.0.dist-info/LICENSE
obsidian_git_uploader-1.0.0.dist-info/METADATA
obsidian_git_uploader-1.0.0.dist-info/WHEEL
obsidian_git_uploader-1.0.0.dist-info/entry_points.txt
obsidian_git_uploader-1.0.0.dist-info/top_level.txt
obsidian_git_uploader-1.0.0.dist-info/RECORD
