Metadata-Version: 2.1
Name: obsidian_git_uploader
Version: 1.0.0
Summary: Obsidian Image Commiter Utility
Home-page: 
Download-URL: 
Author: Revi1337
Author-email: david122123@gmail.com
Keywords: GIT COMMITER,git commiter,IMAGE COMMITER,image commiter
Classifier: Programming Language :: Python :: 3.11
Classifier: License :: OSI Approved :: MIT License
Classifier: Operating System :: Microsoft :: Windows
Requires-Python: >=3
License-File: LICENSE
Requires-Dist: requests
Requires-Dist: beautifulsoup4
Requires-Dist: clipboard
Requires-Dist: Markdown
Requires-Dist: aiohttp
